robot_grpc/GRPCLib.py
robot_grpc/__init__.py
robot_grpc/build/base.d.ts
robot_grpc/build/base.js
robot_grpc/build/invokeMethod.d.ts
robot_grpc/build/invokeMethod.js
robot_grpc/build/runCases.d.ts
robot_grpc/build/runCases.js
robot_grpc/build/types.d.ts
robot_grpc/build/types.js
robot_grpc/node_modules/.yarn-integrity
robot_grpc/node_modules/.bin/check-clang-format
robot_grpc/node_modules/.bin/clang-format
robot_grpc/node_modules/.bin/esparse
robot_grpc/node_modules/.bin/esvalidate
robot_grpc/node_modules/.bin/git-clang-format
robot_grpc/node_modules/.bin/gts
robot_grpc/node_modules/.bin/is-ci
robot_grpc/node_modules/.bin/js-yaml
robot_grpc/node_modules/.bin/jsondiffpatch
robot_grpc/node_modules/.bin/mkdirp
robot_grpc/node_modules/.bin/pbjs
robot_grpc/node_modules/.bin/pbts
robot_grpc/node_modules/.bin/rc
robot_grpc/node_modules/.bin/rimraf
robot_grpc/node_modules/.bin/semver
robot_grpc/node_modules/.bin/sshpk-conv
robot_grpc/node_modules/.bin/sshpk-sign
robot_grpc/node_modules/.bin/sshpk-verify
robot_grpc/node_modules/.bin/tsc
robot_grpc/node_modules/.bin/tslint
robot_grpc/node_modules/.bin/tsserver
robot_grpc/node_modules/.bin/uuid
robot_grpc/node_modules/.bin/which
robot_grpc/node_modules/ajv/.tonic_example.js
robot_grpc/node_modules/ajv/LICENSE
robot_grpc/node_modules/ajv/README.md
robot_grpc/node_modules/ajv/package.json
robot_grpc/node_modules/ansi-align/CHANGELOG.md
robot_grpc/node_modules/ansi-align/LICENSE
robot_grpc/node_modules/ansi-align/README.md
robot_grpc/node_modules/ansi-align/index.js
robot_grpc/node_modules/ansi-align/package.json
robot_grpc/node_modules/ansi-escapes/index.js
robot_grpc/node_modules/ansi-escapes/license
robot_grpc/node_modules/ansi-escapes/package.json
robot_grpc/node_modules/ansi-escapes/readme.md
robot_grpc/node_modules/ansi-regex/index.js
robot_grpc/node_modules/ansi-regex/license
robot_grpc/node_modules/ansi-regex/package.json
robot_grpc/node_modules/ansi-regex/readme.md
robot_grpc/node_modules/ansi-styles/index.js
robot_grpc/node_modules/ci-info/CHANGELOG.md
robot_grpc/node_modules/ci-info/LICENSE
robot_grpc/node_modules/ci-info/README.md
robot_grpc/node_modules/ci-info/index.js
robot_grpc/node_modules/ci-info/package.json
robot_grpc/node_modules/ci-info/vendors.json
robot_grpc/node_modules/hosted-git-info/CHANGELOG.md
robot_grpc/node_modules/hosted-git-info/LICENSE
robot_grpc/node_modules/hosted-git-info/README.md
robot_grpc/node_modules/hosted-git-info/git-host-info.js
robot_grpc/node_modules/hosted-git-info/git-host.js
robot_grpc/node_modules/hosted-git-info/index.js
robot_grpc/node_modules/hosted-git-info/package.json
robot_grpc-0.0.4.dist-info/METADATA
robot_grpc-0.0.4.dist-info/WHEEL
robot_grpc-0.0.4.dist-info/top_level.txt
robot_grpc-0.0.4.dist-info/RECORD
