Metadata-Version: 2.1
Name: robot-grpc
Version: 0.0.4
Summary: robot grpc support
Home-page: https://github.com/pypa/sampleproject
Author: jinkerjiang
Author-email: jinkerjiang@gmail.com
License: UNKNOWN
Platform: UNKNOWN
Classifier: Programming Language :: Python :: 3
Classifier: License :: OSI Approved :: MIT License
Classifier: Operating System :: OS Independent
